eros_core/__init__.py
eros_core/eros_analytics.py
eros_core/eros_layers.py
eros_core/eros_terminal.py
eros_core/main.py
eros_core/transport/drv_generic.py
eros_core/transport/drv_loopback.py
eros_core/transport/drv_serial.py
eros_core/transport/drv_serial_sim.py
eros_core/transport/drv_tcp.py
eros_core/transport/drv_udp.py
eros_core/transport/drv_udp_sim.py
eros_core/transport/drv_zmq.py
eros_core/utils/request_response.py
eros_core-1.0.6.dist-info/METADATA
eros_core-1.0.6.dist-info/WHEEL
eros_core-1.0.6.dist-info/entry_points.txt
eros_core-1.0.6.dist-info/licenses/LICENCE
eros_core-1.0.6.dist-info/RECORD
